{
  "type": "bundle",
  "id": "bundle--5ef98027-5911-4448-a11a-ed89e70c1217",
  "objects": [
    {
      "type": "indicator",
      "spec_version": "2.1",
      "id": "indicator--ccf87282-15e4-43bb-b758-d2e9e3eca140",
      "created": "2026-07-12T17:51:04.000Z",
      "modified": "2026-07-12T17:51:04.000Z",
      "name": "Malicious file (MD5)",
      "pattern_type": "stix",
      "pattern": "[file:hashes.'MD5' = '008cd423ca45134d3343f66cced1d104']",
      "valid_from": "2026-07-12T17:51:04.000Z"
    },
    {
      "type": "indicator",
      "spec_version": "2.1",
      "id": "indicator--6444d91b-1fc7-4710-b753-f0f2ca60419f",
      "created": "2026-07-12T17:51:04.000Z",
      "modified": "2026-07-12T17:51:04.000Z",
      "name": "Malicious file (MD5)",
      "pattern_type": "stix",
      "pattern": "[file:hashes.'MD5' = '038cab0c60c53cf12f048272014024c0']",
      "valid_from": "2026-07-12T17:51:04.000Z"
    },
    {
      "type": "indicator",
      "spec_version": "2.1",
      "id": "indicator--a521c4a9-2b8b-465b-9752-9fe10a3a2d91",
      "created": "2026-07-12T17:51:04.000Z",
      "modified": "2026-07-12T17:51:04.000Z",
      "name": "Malicious file (MD5)",
      "pattern_type": "stix",
      "pattern": "[file:hashes.'MD5' = '06bed0a0906e52c764b3b7016d6a4428']",
      "valid_from": "2026-07-12T17:51:04.000Z"
    },
    {
      "type": "indicator",
      "spec_version": "2.1",
      "id": "indicator--0cc307d4-4bcc-4970-b7a3-f776358b7845",
      "created": "2026-07-12T17:51:04.000Z",
      "modified": "2026-07-12T17:51:04.000Z",
      "name": "Malicious file (MD5)",
      "pattern_type": "stix",
      "pattern": "[file:hashes.'MD5' = '08c069f133ac27cbc02a0ed79e4e87ba']",
      "valid_from": "2026-07-12T17:51:04.000Z"
    },
    {
      "type": "indicator",
      "spec_version": "2.1",
      "id": "indicator--af50aa26-4d76-4dea-8c09-6384ece2961e",
      "created": "2026-07-12T17:51:04.000Z",
      "modified": "2026-07-12T17:51:04.000Z",
      "name": "Malicious file (MD5)",
      "pattern_type": "stix",
      "pattern": "[file:hashes.'MD5' = '09d0517a1f69feff8186655ae3b567e0']",
      "valid_from": "2026-07-12T17:51:04.000Z"
    },
    {
      "type": "indicator",
      "spec_version": "2.1",
      "id": "indicator--bd698e54-43f7-4ec3-a4b9-595edfbd0325",
      "created": "2026-07-12T17:51:04.000Z",
      "modified": "2026-07-12T17:51:04.000Z",
      "name": "Malicious file (MD5)",
      "pattern_type": "stix",
      "pattern": "[file:hashes.'MD5' = '0b1870d57221eec6f3bbef648e71a724']",
      "valid_from": "2026-07-12T17:51:04.000Z"
    },
    {
      "type": "indicator",
      "spec_version": "2.1",
      "id": "indicator--efcabc22-57ca-4cf7-8f80-2b89e3fb5459",
      "created": "2026-07-12T17:51:04.000Z",
      "modified": "2026-07-12T17:51:04.000Z",
      "name": "Malicious file (MD5)",
      "pattern_type": "stix",
      "pattern": "[file:hashes.'MD5' = '0c32bfdf83ecebe3a1399d261dc8ff57']",
      "valid_from": "2026-07-12T17:51:04.000Z"
    },
    {
      "type": "indicator",
      "spec_version": "2.1",
      "id": "indicator--f95a773e-8d2f-48d8-bfa1-ce332a685bcd",
      "created": "2026-07-12T17:51:04.000Z",
      "modified": "2026-07-12T17:51:04.000Z",
      "name": "Malicious file (MD5)",
      "pattern_type": "stix",
      "pattern": "[file:hashes.'MD5' = '10824d14c814524155f2b529cf5fee43']",
      "valid_from": "2026-07-12T17:51:04.000Z"
    },
    {
      "type": "indicator",
      "spec_version": "2.1",
      "id": "indicator--cfb62374-ada0-4dbf-b9f4-b7284e47c113",
      "created": "2026-07-12T17:51:04.000Z",
      "modified": "2026-07-12T17:51:04.000Z",
      "name": "Malicious file (MD5)",
      "pattern_type": "stix",
      "pattern": "[file:hashes.'MD5' = '129225b3e93c17f131bcc2a982ffb09a']",
      "valid_from": "2026-07-12T17:51:04.000Z"
    },
    {
      "type": "indicator",
      "spec_version": "2.1",
      "id": "indicator--4d4a0a52-9ffd-4a4b-a84f-3872c138a1ff",
      "created": "2026-07-12T17:51:04.000Z",
      "modified": "2026-07-12T17:51:04.000Z",
      "name": "Malicious file (MD5)",
      "pattern_type": "stix",
      "pattern": "[file:hashes.'MD5' = '1344e6bc51cea35befb4adff7a25899b']",
      "valid_from": "2026-07-12T17:51:04.000Z"
    },
    {
      "type": "indicator",
      "spec_version": "2.1",
      "id": "indicator--2588b3f3-04d7-47d2-a922-c48c80520d53",
      "created": "2026-07-12T17:51:04.000Z",
      "modified": "2026-07-12T17:51:04.000Z",
      "name": "Malicious file (MD5)",
      "pattern_type": "stix",
      "pattern": "[file:hashes.'MD5' = '1742a9fa35e253614b76ac0f687ba02e']",
      "valid_from": "2026-07-12T17:51:04.000Z"
    },
    {
      "type": "indicator",
      "spec_version": "2.1",
      "id": "indicator--f0f266ac-c418-4251-b5a9-db28da512b81",
      "created": "2026-07-12T17:51:04.000Z",
      "modified": "2026-07-12T17:51:04.000Z",
      "name": "Malicious file (MD5)",
      "pattern_type": "stix",
      "pattern": "[file:hashes.'MD5' = '1c0924f5711a24821921de5ad822213b']",
      "valid_from": "2026-07-12T17:51:04.000Z"
    },
    {
      "type": "indicator",
      "spec_version": "2.1",
      "id": "indicator--81644ab2-c1c9-45dd-af2a-3b8842737ff4",
      "created": "2026-07-12T17:51:04.000Z",
      "modified": "2026-07-12T17:51:04.000Z",
      "name": "Malicious file (MD5)",
      "pattern_type": "stix",
      "pattern": "[file:hashes.'MD5' = '1d09499cb2d7d70df903b60602a58887']",
      "valid_from": "2026-07-12T17:51:04.000Z"
    },
    {
      "type": "indicator",
      "spec_version": "2.1",
      "id": "indicator--f8b3b04a-23b6-4f1b-83dc-8ede6827da93",
      "created": "2026-07-12T17:51:04.000Z",
      "modified": "2026-07-12T17:51:04.000Z",
      "name": "Malicious file (MD5)",
      "pattern_type": "stix",
      "pattern": "[file:hashes.'MD5' = '1e1edf879b2dc6c9892a22bfa5985db1']",
      "valid_from": "2026-07-12T17:51:04.000Z"
    },
    {
      "type": "indicator",
      "spec_version": "2.1",
      "id": "indicator--2211d85b-1b9a-4fc0-8e57-7438ea9997e5",
      "created": "2026-07-12T17:51:04.000Z",
      "modified": "2026-07-12T17:51:04.000Z",
      "name": "Malicious file (MD5)",
      "pattern_type": "stix",
      "pattern": "[file:hashes.'MD5' = '1ff222457f5e0e32adfa8341f260dde7']",
      "valid_from": "2026-07-12T17:51:04.000Z"
    },
    {
      "type": "indicator",
      "spec_version": "2.1",
      "id": "indicator--e7e848b2-1bdd-46de-8b7a-fde394b898d9",
      "created": "2026-07-12T17:51:04.000Z",
      "modified": "2026-07-12T17:51:04.000Z",
      "name": "Malicious file (MD5)",
      "pattern_type": "stix",
      "pattern": "[file:hashes.'MD5' = '242038139842ec79ec1044c64eb0804a']",
      "valid_from": "2026-07-12T17:51:04.000Z"
    },
    {
      "type": "indicator",
      "spec_version": "2.1",
      "id": "indicator--0fcfa5be-2a28-4b87-873e-e23918183e2e",
      "created": "2026-07-12T17:51:04.000Z",
      "modified": "2026-07-12T17:51:04.000Z",
      "name": "Malicious file (MD5)",
      "pattern_type": "stix",
      "pattern": "[file:hashes.'MD5' = '26100db3f56880110a92a2b4742d6eaf']",
      "valid_from": "2026-07-12T17:51:04.000Z"
    },
    {
      "type": "indicator",
      "spec_version": "2.1",
      "id": "indicator--169b3108-1b74-4bae-aa51-f5f6bfcead13",
      "created": "2026-07-12T17:51:04.000Z",
      "modified": "2026-07-12T17:51:04.000Z",
      "name": "Malicious file (MD5)",
      "pattern_type": "stix",
      "pattern": "[file:hashes.'MD5' = '2d5533fb65ebb50a5a5fd53e62d73b9a']",
      "valid_from": "2026-07-12T17:51:04.000Z"
    },
    {
      "type": "indicator",
      "spec_version": "2.1",
      "id": "indicator--174e3cc1-1398-4c7b-b7b7-806c5f5be9cc",
      "created": "2026-07-12T17:51:04.000Z",
      "modified": "2026-07-12T17:51:04.000Z",
      "name": "Malicious file (MD5)",
      "pattern_type": "stix",
      "pattern": "[file:hashes.'MD5' = '2db94ee3ec69988588702bd77999a5d4']",
      "valid_from": "2026-07-12T17:51:04.000Z"
    },
    {
      "type": "indicator",
      "spec_version": "2.1",
      "id": "indicator--f429c118-356a-441f-8cfc-e5ac722fa4f1",
      "created": "2026-07-12T17:51:04.000Z",
      "modified": "2026-07-12T17:51:04.000Z",
      "name": "Malicious file (MD5)",
      "pattern_type": "stix",
      "pattern": "[file:hashes.'MD5' = '2f40bcee90abed0898e92521da17e52d']",
      "valid_from": "2026-07-12T17:51:04.000Z"
    },
    {
      "type": "indicator",
      "spec_version": "2.1",
      "id": "indicator--ccaf3f45-62ed-4143-a607-38adf200c458",
      "created": "2026-07-12T17:51:04.000Z",
      "modified": "2026-07-12T17:51:04.000Z",
      "name": "Malicious file (MD5)",
      "pattern_type": "stix",
      "pattern": "[file:hashes.'MD5' = '36b3be503c6e34613ff50cb28e0f3ddb']",
      "valid_from": "2026-07-12T17:51:04.000Z"
    },
    {
      "type": "indicator",
      "spec_version": "2.1",
      "id": "indicator--edf3fe0b-0c92-40d9-9e6d-ffe9c4d15f05",
      "created": "2026-07-12T17:51:04.000Z",
      "modified": "2026-07-12T17:51:04.000Z",
      "name": "Malicious file (MD5)",
      "pattern_type": "stix",
      "pattern": "[file:hashes.'MD5' = '389a1bbdbf5c91bd1c179227f5ae0923']",
      "valid_from": "2026-07-12T17:51:04.000Z"
    },
    {
      "type": "indicator",
      "spec_version": "2.1",
      "id": "indicator--8581ca29-310f-4990-9f01-01d5c8ceb3a9",
      "created": "2026-07-12T17:51:04.000Z",
      "modified": "2026-07-12T17:51:04.000Z",
      "name": "Malicious file (MD5)",
      "pattern_type": "stix",
      "pattern": "[file:hashes.'MD5' = '3a9b0875fc692944c180b165a83a0d17']",
      "valid_from": "2026-07-12T17:51:04.000Z"
    },
    {
      "type": "indicator",
      "spec_version": "2.1",
      "id": "indicator--e6ab99ec-0159-4388-bb0f-baf68002527f",
      "created": "2026-07-12T17:51:04.000Z",
      "modified": "2026-07-12T17:51:04.000Z",
      "name": "Malicious file (MD5)",
      "pattern_type": "stix",
      "pattern": "[file:hashes.'MD5' = '3b974ff986445e5944c51179d19bd6be']",
      "valid_from": "2026-07-12T17:51:04.000Z"
    },
    {
      "type": "indicator",
      "spec_version": "2.1",
      "id": "indicator--7c7d048b-8f89-44bd-a39b-6dd01fd77bf7",
      "created": "2026-07-12T17:51:04.000Z",
      "modified": "2026-07-12T17:51:04.000Z",
      "name": "Malicious file (MD5)",
      "pattern_type": "stix",
      "pattern": "[file:hashes.'MD5' = '3d9cbc944f9a9e127550ffb4e8394965']",
      "valid_from": "2026-07-12T17:51:04.000Z"
    },
    {
      "type": "indicator",
      "spec_version": "2.1",
      "id": "indicator--8261770e-6f8c-4867-9039-8d0f493a0e43",
      "created": "2026-07-12T17:51:04.000Z",
      "modified": "2026-07-12T17:51:04.000Z",
      "name": "Malicious file (MD5)",
      "pattern_type": "stix",
      "pattern": "[file:hashes.'MD5' = '3ee38b944e5c83922f99641846f7db0c']",
      "valid_from": "2026-07-12T17:51:04.000Z"
    },
    {
      "type": "indicator",
      "spec_version": "2.1",
      "id": "indicator--9399bec9-8c1d-4668-b146-eb58436c7573",
      "created": "2026-07-12T17:51:04.000Z",
      "modified": "2026-07-12T17:51:04.000Z",
      "name": "Malicious file (MD5)",
      "pattern_type": "stix",
      "pattern": "[file:hashes.'MD5' = '4c8a0531653b5398a35c6b1b80ff1350']",
      "valid_from": "2026-07-12T17:51:04.000Z"
    },
    {
      "type": "indicator",
      "spec_version": "2.1",
      "id": "indicator--a70dbc5c-a4d3-4d4c-8d7c-b0db0889f122",
      "created": "2026-07-12T17:51:04.000Z",
      "modified": "2026-07-12T17:51:04.000Z",
      "name": "Malicious file (MD5)",
      "pattern_type": "stix",
      "pattern": "[file:hashes.'MD5' = '5398b7eaa94f0ee570b1c5642b559047']",
      "valid_from": "2026-07-12T17:51:04.000Z"
    },
    {
      "type": "indicator",
      "spec_version": "2.1",
      "id": "indicator--82e57afc-920d-4222-853b-e6c4d4376157",
      "created": "2026-07-12T17:51:04.000Z",
      "modified": "2026-07-12T17:51:04.000Z",
      "name": "Malicious file (MD5)",
      "pattern_type": "stix",
      "pattern": "[file:hashes.'MD5' = '53ba13cc6066adfd67f8098c0a5b8dde']",
      "valid_from": "2026-07-12T17:51:04.000Z"
    },
    {
      "type": "indicator",
      "spec_version": "2.1",
      "id": "indicator--46e9725f-2511-448d-a3c5-8a971965c5a0",
      "created": "2026-07-12T17:51:04.000Z",
      "modified": "2026-07-12T17:51:04.000Z",
      "name": "Malicious file (MD5)",
      "pattern_type": "stix",
      "pattern": "[file:hashes.'MD5' = '54a308f734095d54ae0e1c86c849a2d8']",
      "valid_from": "2026-07-12T17:51:04.000Z"
    },
    {
      "type": "indicator",
      "spec_version": "2.1",
      "id": "indicator--89c7e8f5-2b34-406b-8581-42bc525c7c42",
      "created": "2026-07-12T17:51:04.000Z",
      "modified": "2026-07-12T17:51:04.000Z",
      "name": "Malicious file (MD5)",
      "pattern_type": "stix",
      "pattern": "[file:hashes.'MD5' = '555a6722436d7cf7de396e0c57d32a27']",
      "valid_from": "2026-07-12T17:51:04.000Z"
    },
    {
      "type": "indicator",
      "spec_version": "2.1",
      "id": "indicator--34c8e755-2ef1-499b-bbd3-b6ef213e33b3",
      "created": "2026-07-12T17:51:04.000Z",
      "modified": "2026-07-12T17:51:04.000Z",
      "name": "Malicious file (MD5)",
      "pattern_type": "stix",
      "pattern": "[file:hashes.'MD5' = '56be07e46fd452315008ed246ebbf52b']",
      "valid_from": "2026-07-12T17:51:04.000Z"
    },
    {
      "type": "indicator",
      "spec_version": "2.1",
      "id": "indicator--b03e1fef-fb06-46d6-b28a-a8b97a4c15d4",
      "created": "2026-07-12T17:51:04.000Z",
      "modified": "2026-07-12T17:51:04.000Z",
      "name": "Malicious file (MD5)",
      "pattern_type": "stix",
      "pattern": "[file:hashes.'MD5' = '56d1de3159adbfda20aca593c99901f9']",
      "valid_from": "2026-07-12T17:51:04.000Z"
    },
    {
      "type": "indicator",
      "spec_version": "2.1",
      "id": "indicator--05792535-2e1b-46b3-bcb2-1748e1e54859",
      "created": "2026-07-12T17:51:04.000Z",
      "modified": "2026-07-12T17:51:04.000Z",
      "name": "Malicious file (MD5)",
      "pattern_type": "stix",
      "pattern": "[file:hashes.'MD5' = '579e8bbd6a5bcca89b5acd6fb5db32db']",
      "valid_from": "2026-07-12T17:51:04.000Z"
    },
    {
      "type": "indicator",
      "spec_version": "2.1",
      "id": "indicator--ec75e9e7-4471-45da-87d7-695487f6142a",
      "created": "2026-07-12T17:51:04.000Z",
      "modified": "2026-07-12T17:51:04.000Z",
      "name": "Malicious file (MD5)",
      "pattern_type": "stix",
      "pattern": "[file:hashes.'MD5' = '5e81f72614db42615489266be11b1d09']",
      "valid_from": "2026-07-12T17:51:04.000Z"
    },
    {
      "type": "indicator",
      "spec_version": "2.1",
      "id": "indicator--c5be8d24-1904-42f4-a9ff-71051eec0e85",
      "created": "2026-07-12T17:51:04.000Z",
      "modified": "2026-07-12T17:51:04.000Z",
      "name": "Malicious file (MD5)",
      "pattern_type": "stix",
      "pattern": "[file:hashes.'MD5' = '60f8b115aec8a13b0069efc84fc645f5']",
      "valid_from": "2026-07-12T17:51:04.000Z"
    },
    {
      "type": "indicator",
      "spec_version": "2.1",
      "id": "indicator--cd92349e-5733-433a-a77c-5927f18f0182",
      "created": "2026-07-12T17:51:04.000Z",
      "modified": "2026-07-12T17:51:04.000Z",
      "name": "Malicious file (MD5)",
      "pattern_type": "stix",
      "pattern": "[file:hashes.'MD5' = '61647db645f7cc221046999ef1dbe1d1']",
      "valid_from": "2026-07-12T17:51:04.000Z"
    },
    {
      "type": "indicator",
      "spec_version": "2.1",
      "id": "indicator--4ce8dbd1-1068-4b43-a9b2-b45b4f7e4aa6",
      "created": "2026-07-12T17:51:04.000Z",
      "modified": "2026-07-12T17:51:04.000Z",
      "name": "Malicious file (MD5)",
      "pattern_type": "stix",
      "pattern": "[file:hashes.'MD5' = '62123c39477389d500e74e82782adea5']",
      "valid_from": "2026-07-12T17:51:04.000Z"
    },
    {
      "type": "indicator",
      "spec_version": "2.1",
      "id": "indicator--da33b87c-b342-4fc5-8b5b-4646402f6f77",
      "created": "2026-07-12T17:51:04.000Z",
      "modified": "2026-07-12T17:51:04.000Z",
      "name": "Malicious file (MD5)",
      "pattern_type": "stix",
      "pattern": "[file:hashes.'MD5' = '68e310de44c3165ffffa25bc495d6fc5']",
      "valid_from": "2026-07-12T17:51:04.000Z"
    },
    {
      "type": "indicator",
      "spec_version": "2.1",
      "id": "indicator--058c0272-a54e-482c-b842-d3920200c862",
      "created": "2026-07-12T17:51:04.000Z",
      "modified": "2026-07-12T17:51:04.000Z",
      "name": "Malicious file (MD5)",
      "pattern_type": "stix",
      "pattern": "[file:hashes.'MD5' = '6cf548445c39aff844be96d73c89e376']",
      "valid_from": "2026-07-12T17:51:04.000Z"
    },
    {
      "type": "indicator",
      "spec_version": "2.1",
      "id": "indicator--b0285052-86d6-4b5d-8a41-32b0d6c121d7",
      "created": "2026-07-12T17:51:04.000Z",
      "modified": "2026-07-12T17:51:04.000Z",
      "name": "Malicious file (MD5)",
      "pattern_type": "stix",
      "pattern": "[file:hashes.'MD5' = '6d365de5c5a13006b7cadd6bc6876e84']",
      "valid_from": "2026-07-12T17:51:04.000Z"
    },
    {
      "type": "indicator",
      "spec_version": "2.1",
      "id": "indicator--ccb9af0b-f4e4-43d7-ab70-227ddf45ead8",
      "created": "2026-07-12T17:51:04.000Z",
      "modified": "2026-07-12T17:51:04.000Z",
      "name": "Malicious file (MD5)",
      "pattern_type": "stix",
      "pattern": "[file:hashes.'MD5' = '6dfef58ef68fb7965a23da8be3141af9']",
      "valid_from": "2026-07-12T17:51:04.000Z"
    },
    {
      "type": "indicator",
      "spec_version": "2.1",
      "id": "indicator--faa8957f-60f7-434e-94a9-5a40579b3c10",
      "created": "2026-07-12T17:51:04.000Z",
      "modified": "2026-07-12T17:51:04.000Z",
      "name": "Malicious file (MD5)",
      "pattern_type": "stix",
      "pattern": "[file:hashes.'MD5' = '717ab7624c192f6f8dd38994116c28dc']",
      "valid_from": "2026-07-12T17:51:04.000Z"
    },
    {
      "type": "indicator",
      "spec_version": "2.1",
      "id": "indicator--6de46810-54c4-41e7-9189-45b2c4a4138d",
      "created": "2026-07-12T17:51:04.000Z",
      "modified": "2026-07-12T17:51:04.000Z",
      "name": "Malicious file (MD5)",
      "pattern_type": "stix",
      "pattern": "[file:hashes.'MD5' = '76c819185e3c8b8557a2c3986ab80a7c']",
      "valid_from": "2026-07-12T17:51:04.000Z"
    },
    {
      "type": "indicator",
      "spec_version": "2.1",
      "id": "indicator--c6b830e8-6394-4989-84a6-89e205a3ddb2",
      "created": "2026-07-12T17:51:04.000Z",
      "modified": "2026-07-12T17:51:04.000Z",
      "name": "Malicious file (MD5)",
      "pattern_type": "stix",
      "pattern": "[file:hashes.'MD5' = '78250fa890220821e2b91e31b965de59']",
      "valid_from": "2026-07-12T17:51:04.000Z"
    },
    {
      "type": "indicator",
      "spec_version": "2.1",
      "id": "indicator--7c92b106-bcf1-473f-a0f6-9cecf17fdab2",
      "created": "2026-07-12T17:51:04.000Z",
      "modified": "2026-07-12T17:51:04.000Z",
      "name": "Malicious file (MD5)",
      "pattern_type": "stix",
      "pattern": "[file:hashes.'MD5' = '7d35b4961914ad83a57f8832d8e870d8']",
      "valid_from": "2026-07-12T17:51:04.000Z"
    },
    {
      "type": "indicator",
      "spec_version": "2.1",
      "id": "indicator--0d05a1fc-fda9-450f-a539-5a409712f7be",
      "created": "2026-07-12T17:51:04.000Z",
      "modified": "2026-07-12T17:51:04.000Z",
      "name": "Malicious file (MD5)",
      "pattern_type": "stix",
      "pattern": "[file:hashes.'MD5' = '7da855b2fd9b52f9088e64d656164637']",
      "valid_from": "2026-07-12T17:51:04.000Z"
    },
    {
      "type": "indicator",
      "spec_version": "2.1",
      "id": "indicator--5ee86958-1f8c-4c61-bb6e-56923d7011f2",
      "created": "2026-07-12T17:51:04.000Z",
      "modified": "2026-07-12T17:51:04.000Z",
      "name": "Malicious file (MD5)",
      "pattern_type": "stix",
      "pattern": "[file:hashes.'MD5' = '80e5bde401d6b0ca96015ae9cfeb6535']",
      "valid_from": "2026-07-12T17:51:04.000Z"
    },
    {
      "type": "indicator",
      "spec_version": "2.1",
      "id": "indicator--8baa1bb0-eb0b-4c41-820b-3ab166ad4376",
      "created": "2026-07-12T17:51:04.000Z",
      "modified": "2026-07-12T17:51:04.000Z",
      "name": "Malicious file (MD5)",
      "pattern_type": "stix",
      "pattern": "[file:hashes.'MD5' = '83f66862c0cc40da20236fd6b47138fd']",
      "valid_from": "2026-07-12T17:51:04.000Z"
    },
    {
      "type": "indicator",
      "spec_version": "2.1",
      "id": "indicator--5a52903f-5ee3-4feb-b840-a6f2c3d86753",
      "created": "2026-07-12T17:51:04.000Z",
      "modified": "2026-07-12T17:51:04.000Z",
      "name": "Malicious file (MD5)",
      "pattern_type": "stix",
      "pattern": "[file:hashes.'MD5' = '841b7d3863b49f62d4faa9949ff5df38']",
      "valid_from": "2026-07-12T17:51:04.000Z"
    },
    {
      "type": "indicator",
      "spec_version": "2.1",
      "id": "indicator--d33cc584-8760-4d3b-b6b9-b8cd28e73b94",
      "created": "2026-07-12T17:51:04.000Z",
      "modified": "2026-07-12T17:51:04.000Z",
      "name": "Malicious file (MD5)",
      "pattern_type": "stix",
      "pattern": "[file:hashes.'MD5' = '84bb66a982710c5536143a07d84e8749']",
      "valid_from": "2026-07-12T17:51:04.000Z"
    },
    {
      "type": "indicator",
      "spec_version": "2.1",
      "id": "indicator--dfbeef60-5b1f-40b8-a03d-fa0acfc6c6d2",
      "created": "2026-07-12T17:51:04.000Z",
      "modified": "2026-07-12T17:51:04.000Z",
      "name": "Malicious file (MD5)",
      "pattern_type": "stix",
      "pattern": "[file:hashes.'MD5' = '8db0adf8fd6dc6195d7ae55e37e49f97']",
      "valid_from": "2026-07-12T17:51:04.000Z"
    },
    {
      "type": "indicator",
      "spec_version": "2.1",
      "id": "indicator--b486451c-09e1-4883-b9c6-359a8bc5bc9f",
      "created": "2026-07-12T17:51:04.000Z",
      "modified": "2026-07-12T17:51:04.000Z",
      "name": "Malicious file (MD5)",
      "pattern_type": "stix",
      "pattern": "[file:hashes.'MD5' = '911a21aa999c324dc960d3498eec528e']",
      "valid_from": "2026-07-12T17:51:04.000Z"
    },
    {
      "type": "indicator",
      "spec_version": "2.1",
      "id": "indicator--c1fb9460-fb97-434a-899b-066a8a07e958",
      "created": "2026-07-12T17:51:04.000Z",
      "modified": "2026-07-12T17:51:04.000Z",
      "name": "Malicious file (MD5)",
      "pattern_type": "stix",
      "pattern": "[file:hashes.'MD5' = '96dbdc2651d829bf9ba35674dd4bfcae']",
      "valid_from": "2026-07-12T17:51:04.000Z"
    },
    {
      "type": "indicator",
      "spec_version": "2.1",
      "id": "indicator--5fe7dd61-d237-49c9-95bd-1f95363985ed",
      "created": "2026-07-12T17:51:04.000Z",
      "modified": "2026-07-12T17:51:04.000Z",
      "name": "Malicious file (MD5)",
      "pattern_type": "stix",
      "pattern": "[file:hashes.'MD5' = '9810ea6752112b3569ddc096e1a72e1d']",
      "valid_from": "2026-07-12T17:51:04.000Z"
    },
    {
      "type": "indicator",
      "spec_version": "2.1",
      "id": "indicator--f620e01e-3ca8-4867-98a1-16dc68c02781",
      "created": "2026-07-12T17:51:04.000Z",
      "modified": "2026-07-12T17:51:04.000Z",
      "name": "Malicious file (MD5)",
      "pattern_type": "stix",
      "pattern": "[file:hashes.'MD5' = '9f37fff7e5d22f83fc1c0872ad5332f9']",
      "valid_from": "2026-07-12T17:51:04.000Z"
    },
    {
      "type": "indicator",
      "spec_version": "2.1",
      "id": "indicator--70b6af11-d7a2-455a-a790-8e932d9f39c1",
      "created": "2026-07-12T17:51:04.000Z",
      "modified": "2026-07-12T17:51:04.000Z",
      "name": "Malicious file (MD5)",
      "pattern_type": "stix",
      "pattern": "[file:hashes.'MD5' = 'a36082c998391a3ebaf05ba4f834172c']",
      "valid_from": "2026-07-12T17:51:04.000Z"
    },
    {
      "type": "indicator",
      "spec_version": "2.1",
      "id": "indicator--1b5a93a0-27ac-4958-85c3-ad42521c0dd9",
      "created": "2026-07-12T17:51:04.000Z",
      "modified": "2026-07-12T17:51:04.000Z",
      "name": "Malicious file (MD5)",
      "pattern_type": "stix",
      "pattern": "[file:hashes.'MD5' = 'a3dba01c76571adc0797801ff30f2b90']",
      "valid_from": "2026-07-12T17:51:04.000Z"
    },
    {
      "type": "indicator",
      "spec_version": "2.1",
      "id": "indicator--7570919d-a8c6-4534-8138-e5b504bc021a",
      "created": "2026-07-12T17:51:04.000Z",
      "modified": "2026-07-12T17:51:04.000Z",
      "name": "Malicious file (MD5)",
      "pattern_type": "stix",
      "pattern": "[file:hashes.'MD5' = 'b36968b98046d1b033d84f292e7ca1cb']",
      "valid_from": "2026-07-12T17:51:04.000Z"
    },
    {
      "type": "threat-actor",
      "spec_version": "2.1",
      "id": "threat-actor--7319e8a5-135a-4616-83d7-eb77e00c5fa1",
      "created": "2026-07-12T17:51:04.000Z",
      "modified": "2026-07-12T17:51:04.000Z",
      "name": "4BID"
    }
  ]
}