{
  "type": "bundle",
  "id": "bundle--5aead39d-2092-47ed-861a-36afbe184833",
  "objects": [
    {
      "type": "indicator",
      "spec_version": "2.1",
      "id": "indicator--0b30bf40-ccc2-4c1c-8d9c-6de72a100238",
      "created": "2026-07-23T09:43:44.000Z",
      "modified": "2026-07-23T09:43:44.000Z",
      "name": "Malicious file (MD5)",
      "pattern_type": "stix",
      "pattern": "[file:hashes.'MD5' = 'c3587edc48c37656b29bcd3da9458eea']",
      "valid_from": "2026-07-23T09:43:44.000Z"
    },
    {
      "type": "indicator",
      "spec_version": "2.1",
      "id": "indicator--099d770f-566b-4c75-9772-3057003041b3",
      "created": "2026-07-23T09:43:44.000Z",
      "modified": "2026-07-23T09:43:44.000Z",
      "name": "Malicious file (SHA-256)",
      "pattern_type": "stix",
      "pattern": "[file:hashes.'SHA-256' = '4b7301f02b8312ae6de614981f325dbbabee32166630618fdff74615d9a487ba']",
      "valid_from": "2026-07-23T09:43:44.000Z"
    },
    {
      "type": "indicator",
      "spec_version": "2.1",
      "id": "indicator--ad97a77f-b678-43fe-ac95-c3fbabd1e40e",
      "created": "2026-07-23T09:43:44.000Z",
      "modified": "2026-07-23T09:43:44.000Z",
      "name": "Malicious file (SHA-256)",
      "pattern_type": "stix",
      "pattern": "[file:hashes.'SHA-256' = '59a260716d05c20229c6a46fe0a2fb5b80fa30c9c73a850222d9d3454426a60a']",
      "valid_from": "2026-07-23T09:43:44.000Z"
    },
    {
      "type": "indicator",
      "spec_version": "2.1",
      "id": "indicator--a69f616d-82a6-4d53-a105-400514f6bdc3",
      "created": "2026-07-23T09:43:44.000Z",
      "modified": "2026-07-23T09:43:44.000Z",
      "name": "Malicious file (SHA-256)",
      "pattern_type": "stix",
      "pattern": "[file:hashes.'SHA-256' = '607cb58b8a592885eef5cfbe35ddce962741b0775c575f58cb3a96ca0ee893a6']",
      "valid_from": "2026-07-23T09:43:44.000Z"
    },
    {
      "type": "indicator",
      "spec_version": "2.1",
      "id": "indicator--2fd548f1-8847-45b9-8e34-a287570049a6",
      "created": "2026-07-23T09:43:44.000Z",
      "modified": "2026-07-23T09:43:44.000Z",
      "name": "Malicious file (SHA-256)",
      "pattern_type": "stix",
      "pattern": "[file:hashes.'SHA-256' = 'adbc18f15019ef2ba6890b7996445c14350d57ba772eb33182889bc14ac47085']",
      "valid_from": "2026-07-23T09:43:44.000Z"
    },
    {
      "type": "indicator",
      "spec_version": "2.1",
      "id": "indicator--d8fa6201-6b31-496b-b0e2-3297d8bd68dd",
      "created": "2026-07-23T09:43:44.000Z",
      "modified": "2026-07-23T09:43:44.000Z",
      "name": "Malicious file (SHA-256)",
      "pattern_type": "stix",
      "pattern": "[file:hashes.'SHA-256' = 'b7d50d0406afcd2efd87bf3bf8c4211719ba9817dd2e0ad62af10c933e765e28']",
      "valid_from": "2026-07-23T09:43:44.000Z"
    },
    {
      "type": "indicator",
      "spec_version": "2.1",
      "id": "indicator--118fbcf5-383b-4750-82a5-43cdc288b63e",
      "created": "2026-07-23T09:43:44.000Z",
      "modified": "2026-07-23T09:43:44.000Z",
      "name": "Malicious file (SHA-256)",
      "pattern_type": "stix",
      "pattern": "[file:hashes.'SHA-256' = 'c725815cbb07ab5be8903e74ef8aea46ef9c25e4a3bc626ae94bfc1ae21df6e3']",
      "valid_from": "2026-07-23T09:43:44.000Z"
    },
    {
      "type": "indicator",
      "spec_version": "2.1",
      "id": "indicator--a86969eb-a9bd-4e2d-ba3f-c8c79755f555",
      "created": "2026-07-23T09:43:44.000Z",
      "modified": "2026-07-23T09:43:44.000Z",
      "name": "Malicious file (SHA-256)",
      "pattern_type": "stix",
      "pattern": "[file:hashes.'SHA-256' = 'e3ec5926a167d6e3359f98cdfb7ac3b2cce97652843056505d02e6d2898573c6']",
      "valid_from": "2026-07-23T09:43:44.000Z"
    },
    {
      "type": "indicator",
      "spec_version": "2.1",
      "id": "indicator--46820aca-1844-405e-83d0-6bea2d6d39be",
      "created": "2026-07-23T09:43:44.000Z",
      "modified": "2026-07-23T09:43:44.000Z",
      "name": "C2/infra domain",
      "pattern_type": "stix",
      "pattern": "[domain-name:value = 'helloxcherry.com']",
      "valid_from": "2026-07-23T09:43:44.000Z"
    }
  ]
}