{
  "type": "bundle",
  "id": "bundle--7a67b9bc-3015-4194-bb6f-48ede9baaf86",
  "objects": [
    {
      "type": "indicator",
      "spec_version": "2.1",
      "id": "indicator--298e28b5-ee43-422e-b83b-e6c098da2590",
      "created": "2026-07-23T16:31:49.000Z",
      "modified": "2026-07-23T16:31:49.000Z",
      "name": "Malicious file (SHA-256)",
      "pattern_type": "stix",
      "pattern": "[file:hashes.'SHA-256' = '131877a052f62750d815cf55d4c14f606a26025e3094e1b8bb18bd1668e3beaa']",
      "valid_from": "2026-07-23T16:31:49.000Z"
    },
    {
      "type": "threat-actor",
      "spec_version": "2.1",
      "id": "threat-actor--dfce55fb-8c5d-4df2-b0ef-6b4e51b6e0d6",
      "created": "2026-07-23T16:31:49.000Z",
      "modified": "2026-07-23T16:31:49.000Z",
      "name": "Storm-1567"
    }
  ]
}