{
  "type": "bundle",
  "id": "bundle--b0e40dbb-f96f-43ce-8350-fd06b9a56308",
  "objects": [
    {
      "type": "indicator",
      "spec_version": "2.1",
      "id": "indicator--26e57756-3885-4878-8a80-4dab34adadfa",
      "created": "2026-07-13T16:30:27.000Z",
      "modified": "2026-07-13T16:30:27.000Z",
      "name": "Malicious file (SHA-256)",
      "pattern_type": "stix",
      "pattern": "[file:hashes.'SHA-256' = '2add9429d2822ae0c01c08bbd66c3a110ef2e9c3a00cded1477657e9024e391e']",
      "valid_from": "2026-07-13T16:30:27.000Z"
    },
    {
      "type": "indicator",
      "spec_version": "2.1",
      "id": "indicator--50fb2950-2945-42e9-bdc5-c96084e129c2",
      "created": "2026-07-13T16:30:27.000Z",
      "modified": "2026-07-13T16:30:27.000Z",
      "name": "Malicious file (SHA-256)",
      "pattern_type": "stix",
      "pattern": "[file:hashes.'SHA-256' = 'cb65f5873c72d707371ec56fb8ba501a5c7f5940e9c5a2d28c9b379ce216900c']",
      "valid_from": "2026-07-13T16:30:27.000Z"
    },
    {
      "type": "indicator",
      "spec_version": "2.1",
      "id": "indicator--cc87fad5-4a4b-407d-bcbb-559a589efa55",
      "created": "2026-07-13T16:30:27.000Z",
      "modified": "2026-07-13T16:30:27.000Z",
      "name": "Malicious file (SHA-256)",
      "pattern_type": "stix",
      "pattern": "[file:hashes.'SHA-256' = '1c170b7470d507378ddb78e9d66305f1184e965baaf2d27ededb23a318a58953']",
      "valid_from": "2026-07-13T16:30:27.000Z"
    },
    {
      "type": "indicator",
      "spec_version": "2.1",
      "id": "indicator--3d5fcf66-8c99-4f69-8e41-2fb8656363ef",
      "created": "2026-07-13T16:30:27.000Z",
      "modified": "2026-07-13T16:30:27.000Z",
      "name": "Malicious file (SHA-256)",
      "pattern_type": "stix",
      "pattern": "[file:hashes.'SHA-256' = '507b2fcdae058cebbd550965b90c44e878d7a2463058c846eeb68f0dc1b48eda']",
      "valid_from": "2026-07-13T16:30:27.000Z"
    },
    {
      "type": "indicator",
      "spec_version": "2.1",
      "id": "indicator--40ee8b7a-1aa7-4082-a232-8a8626d25a1d",
      "created": "2026-07-13T16:30:27.000Z",
      "modified": "2026-07-13T16:30:27.000Z",
      "name": "Malicious file (SHA-256)",
      "pattern_type": "stix",
      "pattern": "[file:hashes.'SHA-256' = 'bf338d88f60c0d352cd0d1b5e4bc6a1d9f1ac8fe1df48516ec0042cafda821e9']",
      "valid_from": "2026-07-13T16:30:27.000Z"
    },
    {
      "type": "indicator",
      "spec_version": "2.1",
      "id": "indicator--b0420590-fedb-4043-ae35-c74280dc5e9d",
      "created": "2026-07-13T16:30:27.000Z",
      "modified": "2026-07-13T16:30:27.000Z",
      "name": "Malicious file (SHA-256)",
      "pattern_type": "stix",
      "pattern": "[file:hashes.'SHA-256' = 'f668bd551859007cf2cc2a62bf0bf5414870a04e9782590c9bf85c849ddb308b']",
      "valid_from": "2026-07-13T16:30:27.000Z"
    },
    {
      "type": "indicator",
      "spec_version": "2.1",
      "id": "indicator--29cf10ba-6f49-4f32-9d2b-3ac5341cc502",
      "created": "2026-07-13T16:30:27.000Z",
      "modified": "2026-07-13T16:30:27.000Z",
      "name": "Malicious file (SHA-256)",
      "pattern_type": "stix",
      "pattern": "[file:hashes.'SHA-256' = 'f9d2907d6b1de3078a0f111cc98764a92baf5ebd06cc8ab02637a65eff3b7f3a']",
      "valid_from": "2026-07-13T16:30:27.000Z"
    },
    {
      "type": "indicator",
      "spec_version": "2.1",
      "id": "indicator--2dacf0c0-0441-44e0-b1d3-1dadd2363d8d",
      "created": "2026-07-13T16:30:27.000Z",
      "modified": "2026-07-13T16:30:27.000Z",
      "name": "Malicious file (SHA-256)",
      "pattern_type": "stix",
      "pattern": "[file:hashes.'SHA-256' = '0a9bc91e7ea2c3931f662eea37c00c7c26c8996b65f6f7afe6cce8f6114f94b6']",
      "valid_from": "2026-07-13T16:30:27.000Z"
    },
    {
      "type": "indicator",
      "spec_version": "2.1",
      "id": "indicator--ec6c3b5e-b5d0-4539-bdda-5ca903597a06",
      "created": "2026-07-13T16:30:27.000Z",
      "modified": "2026-07-13T16:30:27.000Z",
      "name": "Malicious file (SHA-256)",
      "pattern_type": "stix",
      "pattern": "[file:hashes.'SHA-256' = '39dd1bd3bccc314d8933e5c41ed2ab084e4e20af569f77b7cf09abc5855b9483']",
      "valid_from": "2026-07-13T16:30:27.000Z"
    },
    {
      "type": "indicator",
      "spec_version": "2.1",
      "id": "indicator--830858f8-fc3d-4f87-9210-84270aa8b8f2",
      "created": "2026-07-13T16:30:27.000Z",
      "modified": "2026-07-13T16:30:27.000Z",
      "name": "Malicious file (SHA-256)",
      "pattern_type": "stix",
      "pattern": "[file:hashes.'SHA-256' = '1ebbdf3671cd5ca25a8a8e7ca2f6e46dd22c631e01bfcc5c909ae2fd680bf458']",
      "valid_from": "2026-07-13T16:30:27.000Z"
    },
    {
      "type": "indicator",
      "spec_version": "2.1",
      "id": "indicator--60ddcbed-9000-49f3-8f80-3c4360fb1244",
      "created": "2026-07-13T16:30:27.000Z",
      "modified": "2026-07-13T16:30:27.000Z",
      "name": "Malicious file (MD5)",
      "pattern_type": "stix",
      "pattern": "[file:hashes.'MD5' = 'a113090d748d0dac7d488c97f1305af2']",
      "valid_from": "2026-07-13T16:30:27.000Z"
    },
    {
      "type": "indicator",
      "spec_version": "2.1",
      "id": "indicator--2be71fab-ef05-400e-bf0f-a1d9f2bc8bb9",
      "created": "2026-07-13T16:30:27.000Z",
      "modified": "2026-07-13T16:30:27.000Z",
      "name": "Malicious file (MD5)",
      "pattern_type": "stix",
      "pattern": "[file:hashes.'MD5' = '473c65b922d3308a98c6b76c7d99a196']",
      "valid_from": "2026-07-13T16:30:27.000Z"
    },
    {
      "type": "indicator",
      "spec_version": "2.1",
      "id": "indicator--c6a68e63-320b-45cc-a6f5-a2f5844d59ce",
      "created": "2026-07-13T16:30:27.000Z",
      "modified": "2026-07-13T16:30:27.000Z",
      "name": "Malicious file (MD5)",
      "pattern_type": "stix",
      "pattern": "[file:hashes.'MD5' = '4082096ec0b8f723a79a224a6b6d37cd']",
      "valid_from": "2026-07-13T16:30:27.000Z"
    },
    {
      "type": "indicator",
      "spec_version": "2.1",
      "id": "indicator--e23a2668-e924-4bb5-a1a4-0fcdef458042",
      "created": "2026-07-13T16:30:27.000Z",
      "modified": "2026-07-13T16:30:27.000Z",
      "name": "Malicious file (MD5)",
      "pattern_type": "stix",
      "pattern": "[file:hashes.'MD5' = '587a464ffc174288d3f66d1845133229']",
      "valid_from": "2026-07-13T16:30:27.000Z"
    },
    {
      "type": "indicator",
      "spec_version": "2.1",
      "id": "indicator--cf0cb652-0d21-478c-a171-094866e488f2",
      "created": "2026-07-13T16:30:27.000Z",
      "modified": "2026-07-13T16:30:27.000Z",
      "name": "Malicious file (MD5)",
      "pattern_type": "stix",
      "pattern": "[file:hashes.'MD5' = '8ca36b9cbd72d1f4ab4a9c8fcf85fe7e']",
      "valid_from": "2026-07-13T16:30:27.000Z"
    },
    {
      "type": "indicator",
      "spec_version": "2.1",
      "id": "indicator--fc1283e3-fdcc-4091-a1cd-f39dd083768d",
      "created": "2026-07-13T16:30:27.000Z",
      "modified": "2026-07-13T16:30:27.000Z",
      "name": "Malicious file (MD5)",
      "pattern_type": "stix",
      "pattern": "[file:hashes.'MD5' = 'addf25d1f994729f2d3cbb3d0ab49897']",
      "valid_from": "2026-07-13T16:30:27.000Z"
    },
    {
      "type": "indicator",
      "spec_version": "2.1",
      "id": "indicator--e27e604d-3e84-43a7-bbda-7c7b7bb4513c",
      "created": "2026-07-13T16:30:27.000Z",
      "modified": "2026-07-13T16:30:27.000Z",
      "name": "Malicious file (MD5)",
      "pattern_type": "stix",
      "pattern": "[file:hashes.'MD5' = 'ea610ea6a8d69cb1e93fb79d4a8fa26f']",
      "valid_from": "2026-07-13T16:30:27.000Z"
    },
    {
      "type": "indicator",
      "spec_version": "2.1",
      "id": "indicator--2c6fed3a-017a-4213-8626-ff9782ca6319",
      "created": "2026-07-13T16:30:27.000Z",
      "modified": "2026-07-13T16:30:27.000Z",
      "name": "Malicious file (SHA-1)",
      "pattern_type": "stix",
      "pattern": "[file:hashes.'SHA-1' = '02462fa8f816b2ff21898612552d7845abcb9070']",
      "valid_from": "2026-07-13T16:30:27.000Z"
    },
    {
      "type": "indicator",
      "spec_version": "2.1",
      "id": "indicator--44f290f2-38a7-4d17-92a8-e04b8b20cf8a",
      "created": "2026-07-13T16:30:27.000Z",
      "modified": "2026-07-13T16:30:27.000Z",
      "name": "Malicious file (SHA-1)",
      "pattern_type": "stix",
      "pattern": "[file:hashes.'SHA-1' = '1f34a8fad545554420650a8518d4199431fc2920']",
      "valid_from": "2026-07-13T16:30:27.000Z"
    },
    {
      "type": "indicator",
      "spec_version": "2.1",
      "id": "indicator--b83b734b-4a07-4c46-86b9-1f096c67018c",
      "created": "2026-07-13T16:30:27.000Z",
      "modified": "2026-07-13T16:30:27.000Z",
      "name": "Malicious file (SHA-1)",
      "pattern_type": "stix",
      "pattern": "[file:hashes.'SHA-1' = '23e076f5db64fb51226ef56a60bae6424b06a432']",
      "valid_from": "2026-07-13T16:30:27.000Z"
    },
    {
      "type": "indicator",
      "spec_version": "2.1",
      "id": "indicator--14e2dc74-e8ea-4802-bcda-fdc851575c36",
      "created": "2026-07-13T16:30:27.000Z",
      "modified": "2026-07-13T16:30:27.000Z",
      "name": "Malicious file (SHA-1)",
      "pattern_type": "stix",
      "pattern": "[file:hashes.'SHA-1' = '42428f21b0114e390c6129f1fb24b42e97a8f7f7']",
      "valid_from": "2026-07-13T16:30:27.000Z"
    },
    {
      "type": "indicator",
      "spec_version": "2.1",
      "id": "indicator--ca1dc3d5-5958-44a2-86c8-9bd9ffd1be5d",
      "created": "2026-07-13T16:30:27.000Z",
      "modified": "2026-07-13T16:30:27.000Z",
      "name": "Malicious file (SHA-1)",
      "pattern_type": "stix",
      "pattern": "[file:hashes.'SHA-1' = '4f29c2059dcba412c3ef0100e839cf85fb0f62c1']",
      "valid_from": "2026-07-13T16:30:27.000Z"
    },
    {
      "type": "indicator",
      "spec_version": "2.1",
      "id": "indicator--be5207d6-5f49-496e-a9fb-7b33dfad2575",
      "created": "2026-07-13T16:30:27.000Z",
      "modified": "2026-07-13T16:30:27.000Z",
      "name": "Malicious file (SHA-1)",
      "pattern_type": "stix",
      "pattern": "[file:hashes.'SHA-1' = 'ad102478adda75ef6c6985187fc1e8b0bc1edded']",
      "valid_from": "2026-07-13T16:30:27.000Z"
    },
    {
      "type": "indicator",
      "spec_version": "2.1",
      "id": "indicator--ce1fed63-6ab6-46a2-8a74-a4eb1c4e9b39",
      "created": "2026-07-13T16:30:27.000Z",
      "modified": "2026-07-13T16:30:27.000Z",
      "name": "Malicious file (SHA-1)",
      "pattern_type": "stix",
      "pattern": "[file:hashes.'SHA-1' = 'd8d789af0ede2ce38a50b516f7603376589ae141']",
      "valid_from": "2026-07-13T16:30:27.000Z"
    },
    {
      "type": "threat-actor",
      "spec_version": "2.1",
      "id": "threat-actor--a47f9440-c940-404a-b249-2b4ddefd6067",
      "created": "2026-07-13T16:30:27.000Z",
      "modified": "2026-07-13T16:30:27.000Z",
      "name": "Gamaredon"
    }
  ]
}