{
  "type": "bundle",
  "id": "bundle--fe770b99-6c72-47d8-8dcd-8bf13eb0d561",
  "objects": [
    {
      "type": "indicator",
      "spec_version": "2.1",
      "id": "indicator--d6b32412-8f50-4c0a-b045-72427e01a6be",
      "created": "2026-07-15T09:20:12.000Z",
      "modified": "2026-07-15T09:20:12.000Z",
      "name": "C2/infra domain",
      "pattern_type": "stix",
      "pattern": "[domain-name:value = 'tomorrowland-booking.com']",
      "valid_from": "2026-07-15T09:20:12.000Z"
    },
    {
      "type": "indicator",
      "spec_version": "2.1",
      "id": "indicator--134a78b3-1c11-4277-b489-48cc5fa60ccc",
      "created": "2026-07-15T09:20:12.000Z",
      "modified": "2026-07-15T09:20:12.000Z",
      "name": "C2/infra domain",
      "pattern_type": "stix",
      "pattern": "[domain-name:value = 'belgium-tomorrowlland.com']",
      "valid_from": "2026-07-15T09:20:12.000Z"
    },
    {
      "type": "indicator",
      "spec_version": "2.1",
      "id": "indicator--9472f0de-d93b-4446-af8a-04c99c3bb530",
      "created": "2026-07-15T09:20:12.000Z",
      "modified": "2026-07-15T09:20:12.000Z",
      "name": "C2/infra domain",
      "pattern_type": "stix",
      "pattern": "[domain-name:value = 'belgium-tomorrowlland.info']",
      "valid_from": "2026-07-15T09:20:12.000Z"
    },
    {
      "type": "indicator",
      "spec_version": "2.1",
      "id": "indicator--fb067724-3c57-4674-812b-6e48593dffb0",
      "created": "2026-07-15T09:20:12.000Z",
      "modified": "2026-07-15T09:20:12.000Z",
      "name": "C2/infra domain",
      "pattern_type": "stix",
      "pattern": "[domain-name:value = 'belgiumtomoorrowland.com']",
      "valid_from": "2026-07-15T09:20:12.000Z"
    },
    {
      "type": "indicator",
      "spec_version": "2.1",
      "id": "indicator--6aa6afec-4bfa-4d13-8c24-02e2890f4320",
      "created": "2026-07-15T09:20:12.000Z",
      "modified": "2026-07-15T09:20:12.000Z",
      "name": "C2/infra domain",
      "pattern_type": "stix",
      "pattern": "[domain-name:value = 'festreisen.com']",
      "valid_from": "2026-07-15T09:20:12.000Z"
    },
    {
      "type": "indicator",
      "spec_version": "2.1",
      "id": "indicator--3a4e86b2-4fa3-43fc-b24f-7d7f6e5803ea",
      "created": "2026-07-15T09:20:12.000Z",
      "modified": "2026-07-15T09:20:12.000Z",
      "name": "C2/infra domain",
      "pattern_type": "stix",
      "pattern": "[domain-name:value = 'jedemenatomorrowland.cz']",
      "valid_from": "2026-07-15T09:20:12.000Z"
    },
    {
      "type": "indicator",
      "spec_version": "2.1",
      "id": "indicator--12034f79-e7ca-4134-bfae-7485455df775",
      "created": "2026-07-15T09:20:12.000Z",
      "modified": "2026-07-15T09:20:12.000Z",
      "name": "C2/infra domain",
      "pattern_type": "stix",
      "pattern": "[domain-name:value = 'mcsdirect.tech']",
      "valid_from": "2026-07-15T09:20:12.000Z"
    },
    {
      "type": "indicator",
      "spec_version": "2.1",
      "id": "indicator--11ea8221-7818-4529-ba8e-1ea27820768a",
      "created": "2026-07-15T09:20:12.000Z",
      "modified": "2026-07-15T09:20:12.000Z",
      "name": "C2/infra domain",
      "pattern_type": "stix",
      "pattern": "[domain-name:value = 'tmrlnd.shop']",
      "valid_from": "2026-07-15T09:20:12.000Z"
    },
    {
      "type": "indicator",
      "spec_version": "2.1",
      "id": "indicator--420d525d-d38e-4413-8035-3c9ca4e19833",
      "created": "2026-07-15T09:20:12.000Z",
      "modified": "2026-07-15T09:20:12.000Z",
      "name": "C2/infra domain",
      "pattern_type": "stix",
      "pattern": "[domain-name:value = 'tomorrowland-2026.com']",
      "valid_from": "2026-07-15T09:20:12.000Z"
    },
    {
      "type": "indicator",
      "spec_version": "2.1",
      "id": "indicator--6a3652ff-d4bd-4d60-af81-260c3cfcddae",
      "created": "2026-07-15T09:20:12.000Z",
      "modified": "2026-07-15T09:20:12.000Z",
      "name": "C2/infra domain",
      "pattern_type": "stix",
      "pattern": "[domain-name:value = 'tomorrowland-book.com']",
      "valid_from": "2026-07-15T09:20:12.000Z"
    },
    {
      "type": "indicator",
      "spec_version": "2.1",
      "id": "indicator--bef74f3d-cc87-48fc-a021-676127b82932",
      "created": "2026-07-15T09:20:12.000Z",
      "modified": "2026-07-15T09:20:12.000Z",
      "name": "C2/infra domain",
      "pattern_type": "stix",
      "pattern": "[domain-name:value = 'tomorrowlandbuytickets.com']",
      "valid_from": "2026-07-15T09:20:12.000Z"
    },
    {
      "type": "indicator",
      "spec_version": "2.1",
      "id": "indicator--668e06bb-082e-4296-bc42-4d6fadfdc191",
      "created": "2026-07-15T09:20:12.000Z",
      "modified": "2026-07-15T09:20:12.000Z",
      "name": "C2/infra domain",
      "pattern_type": "stix",
      "pattern": "[domain-name:value = 'tomorrowlandtickets.org']",
      "valid_from": "2026-07-15T09:20:12.000Z"
    },
    {
      "type": "indicator",
      "spec_version": "2.1",
      "id": "indicator--f3579c8f-f2fd-485c-923f-5a76b0fada1c",
      "created": "2026-07-15T09:20:12.000Z",
      "modified": "2026-07-15T09:20:12.000Z",
      "name": "C2/infra domain",
      "pattern_type": "stix",
      "pattern": "[domain-name:value = 'tomorrowlland.com']",
      "valid_from": "2026-07-15T09:20:12.000Z"
    },
    {
      "type": "indicator",
      "spec_version": "2.1",
      "id": "indicator--f68c972f-7c7d-4c59-976b-ee00c9a44bcc",
      "created": "2026-07-15T09:20:12.000Z",
      "modified": "2026-07-15T09:20:12.000Z",
      "name": "C2/infra domain",
      "pattern_type": "stix",
      "pattern": "[domain-name:value = 'winter-tomorrowlland.com']",
      "valid_from": "2026-07-15T09:20:12.000Z"
    },
    {
      "type": "indicator",
      "spec_version": "2.1",
      "id": "indicator--f25bc4e4-4a5a-4db7-8eb1-5a1edf36e59f",
      "created": "2026-07-15T09:20:12.000Z",
      "modified": "2026-07-15T09:20:12.000Z",
      "name": "C2/infra domain",
      "pattern_type": "stix",
      "pattern": "[domain-name:value = 'belgium.tomorrowland.now']",
      "valid_from": "2026-07-15T09:20:12.000Z"
    },
    {
      "type": "indicator",
      "spec_version": "2.1",
      "id": "indicator--fc77ae2a-0e87-4a04-baa9-63ab53d92b43",
      "created": "2026-07-15T09:20:12.000Z",
      "modified": "2026-07-15T09:20:12.000Z",
      "name": "C2/infra domain",
      "pattern_type": "stix",
      "pattern": "[domain-name:value = 'tomorrowland.events.cryptonexum.com']",
      "valid_from": "2026-07-15T09:20:12.000Z"
    },
    {
      "type": "indicator",
      "spec_version": "2.1",
      "id": "indicator--7ddd627e-b62c-4b3c-bf87-a17925401c1c",
      "created": "2026-07-15T09:20:12.000Z",
      "modified": "2026-07-15T09:20:12.000Z",
      "name": "C2/infra domain",
      "pattern_type": "stix",
      "pattern": "[domain-name:value = 'www.vvipevent.com']",
      "valid_from": "2026-07-15T09:20:12.000Z"
    },
    {
      "type": "indicator",
      "spec_version": "2.1",
      "id": "indicator--a65260c6-497b-467d-8078-c7b556e542ab",
      "created": "2026-07-15T09:20:12.000Z",
      "modified": "2026-07-15T09:20:12.000Z",
      "name": "C2/infra domain",
      "pattern_type": "stix",
      "pattern": "[domain-name:value = 'billetterie-tomorrowland.com']",
      "valid_from": "2026-07-15T09:20:12.000Z"
    },
    {
      "type": "indicator",
      "spec_version": "2.1",
      "id": "indicator--e4ce6ddf-d10d-4399-87ea-fe496ecfed90",
      "created": "2026-07-15T09:20:12.000Z",
      "modified": "2026-07-15T09:20:12.000Z",
      "name": "C2/infra IP",
      "pattern_type": "stix",
      "pattern": "[ipv4-addr:value = '45.131.214.47']",
      "valid_from": "2026-07-15T09:20:12.000Z"
    },
    {
      "type": "indicator",
      "spec_version": "2.1",
      "id": "indicator--26b5c669-ed47-4db9-8636-0528fb21d572",
      "created": "2026-07-15T09:20:12.000Z",
      "modified": "2026-07-15T09:20:12.000Z",
      "name": "C2/infra IP",
      "pattern_type": "stix",
      "pattern": "[ipv4-addr:value = '45.142.140.75']",
      "valid_from": "2026-07-15T09:20:12.000Z"
    }
  ]
}