{
  "type": "bundle",
  "id": "bundle--3062e5d4-eead-4bc2-9af9-0ca9adbd36fc",
  "objects": [
    {
      "type": "indicator",
      "spec_version": "2.1",
      "id": "indicator--3e59d46d-8e78-462d-81a1-49b4a8d401e4",
      "created": "2026-07-18T10:08:02.000Z",
      "modified": "2026-07-18T10:08:02.000Z",
      "name": "C2/infra domain",
      "pattern_type": "stix",
      "pattern": "[domain-name:value = 'acasiallc.shop']",
      "valid_from": "2026-07-18T10:08:02.000Z"
    },
    {
      "type": "indicator",
      "spec_version": "2.1",
      "id": "indicator--06ae406a-abc2-4115-b2f5-3eb823d84de7",
      "created": "2026-07-18T10:08:02.000Z",
      "modified": "2026-07-18T10:08:02.000Z",
      "name": "C2/infra domain",
      "pattern_type": "stix",
      "pattern": "[domain-name:value = 'amdocsllc.shop']",
      "valid_from": "2026-07-18T10:08:02.000Z"
    },
    {
      "type": "indicator",
      "spec_version": "2.1",
      "id": "indicator--a1861c3b-b479-4fe8-843e-6fb57d489212",
      "created": "2026-07-18T10:08:02.000Z",
      "modified": "2026-07-18T10:08:02.000Z",
      "name": "C2/infra domain",
      "pattern_type": "stix",
      "pattern": "[domain-name:value = 'ansysllc.shop']",
      "valid_from": "2026-07-18T10:08:02.000Z"
    },
    {
      "type": "indicator",
      "spec_version": "2.1",
      "id": "indicator--cf670e20-78b0-4bb1-acf3-19e34294c786",
      "created": "2026-07-18T10:08:02.000Z",
      "modified": "2026-07-18T10:08:02.000Z",
      "name": "C2/infra domain",
      "pattern_type": "stix",
      "pattern": "[domain-name:value = 'cimentosservices.online']",
      "valid_from": "2026-07-18T10:08:02.000Z"
    },
    {
      "type": "indicator",
      "spec_version": "2.1",
      "id": "indicator--e45f54e8-615f-4f51-9d7d-c4253bcadccc",
      "created": "2026-07-18T10:08:02.000Z",
      "modified": "2026-07-18T10:08:02.000Z",
      "name": "C2/infra domain",
      "pattern_type": "stix",
      "pattern": "[domain-name:value = 'epsilongroup.online']",
      "valid_from": "2026-07-18T10:08:02.000Z"
    },
    {
      "type": "indicator",
      "spec_version": "2.1",
      "id": "indicator--42070c08-9ae7-41dd-b6a5-7d8bfb18ef0e",
      "created": "2026-07-18T10:08:02.000Z",
      "modified": "2026-07-18T10:08:02.000Z",
      "name": "C2/infra domain",
      "pattern_type": "stix",
      "pattern": "[domain-name:value = 'softinsallc.online']",
      "valid_from": "2026-07-18T10:08:02.000Z"
    },
    {
      "type": "indicator",
      "spec_version": "2.1",
      "id": "indicator--08f2102a-4f43-4600-80c1-5a1f4062b49c",
      "created": "2026-07-18T10:08:02.000Z",
      "modified": "2026-07-18T10:08:02.000Z",
      "name": "C2/infra domain",
      "pattern_type": "stix",
      "pattern": "[domain-name:value = 'taicom.top']",
      "valid_from": "2026-07-18T10:08:02.000Z"
    },
    {
      "type": "indicator",
      "spec_version": "2.1",
      "id": "indicator--07e43241-fbf3-48f5-8bfc-eaadf5edaa03",
      "created": "2026-07-18T10:08:02.000Z",
      "modified": "2026-07-18T10:08:02.000Z",
      "name": "C2/infra domain",
      "pattern_type": "stix",
      "pattern": "[domain-name:value = 'krysegroupllc.online']",
      "valid_from": "2026-07-18T10:08:02.000Z"
    },
    {
      "type": "indicator",
      "spec_version": "2.1",
      "id": "indicator--9647bcd5-5e94-4747-88e6-09a898d48979",
      "created": "2026-07-18T10:08:02.000Z",
      "modified": "2026-07-18T10:08:02.000Z",
      "name": "C2/infra domain",
      "pattern_type": "stix",
      "pattern": "[domain-name:value = 'shengan-light.com.tw']",
      "valid_from": "2026-07-18T10:08:02.000Z"
    },
    {
      "type": "indicator",
      "spec_version": "2.1",
      "id": "indicator--99f58023-c853-4e32-894c-e6c42b68169b",
      "created": "2026-07-18T10:08:02.000Z",
      "modified": "2026-07-18T10:08:02.000Z",
      "name": "C2/infra IP",
      "pattern_type": "stix",
      "pattern": "[ipv4-addr:value = '194.156.79.122']",
      "valid_from": "2026-07-18T10:08:02.000Z"
    },
    {
      "type": "indicator",
      "spec_version": "2.1",
      "id": "indicator--5480debd-8a70-44a3-8ce1-8c93a764ac23",
      "created": "2026-07-18T10:08:02.000Z",
      "modified": "2026-07-18T10:08:02.000Z",
      "name": "C2/infra IP",
      "pattern_type": "stix",
      "pattern": "[ipv4-addr:value = '85.17.40.98']",
      "valid_from": "2026-07-18T10:08:02.000Z"
    },
    {
      "type": "indicator",
      "spec_version": "2.1",
      "id": "indicator--36f8f0b8-8b0b-407e-a9c4-5e01aa3c7f05",
      "created": "2026-07-18T10:08:02.000Z",
      "modified": "2026-07-18T10:08:02.000Z",
      "name": "C2/infra IP",
      "pattern_type": "stix",
      "pattern": "[ipv4-addr:value = '185.252.24.52']",
      "valid_from": "2026-07-18T10:08:02.000Z"
    },
    {
      "type": "indicator",
      "spec_version": "2.1",
      "id": "indicator--9191650e-e892-4864-a5cb-72fc0f58b9dd",
      "created": "2026-07-18T10:08:02.000Z",
      "modified": "2026-07-18T10:08:02.000Z",
      "name": "C2/infra IP",
      "pattern_type": "stix",
      "pattern": "[ipv4-addr:value = '176.114.8.101']",
      "valid_from": "2026-07-18T10:08:02.000Z"
    },
    {
      "type": "indicator",
      "spec_version": "2.1",
      "id": "indicator--7ddcd417-16fc-492c-87a1-268e86bc461b",
      "created": "2026-07-18T10:08:02.000Z",
      "modified": "2026-07-18T10:08:02.000Z",
      "name": "C2/infra IP",
      "pattern_type": "stix",
      "pattern": "[ipv4-addr:value = '176.114.8.90']",
      "valid_from": "2026-07-18T10:08:02.000Z"
    },
    {
      "type": "indicator",
      "spec_version": "2.1",
      "id": "indicator--c05a4b69-762f-4b23-914d-bebec0296a87",
      "created": "2026-07-18T10:08:02.000Z",
      "modified": "2026-07-18T10:08:02.000Z",
      "name": "C2/infra IP",
      "pattern_type": "stix",
      "pattern": "[ipv4-addr:value = '185.252.24.74']",
      "valid_from": "2026-07-18T10:08:02.000Z"
    },
    {
      "type": "indicator",
      "spec_version": "2.1",
      "id": "indicator--1a56ae3e-29b7-4b8f-92d7-d65f1e543c27",
      "created": "2026-07-18T10:08:02.000Z",
      "modified": "2026-07-18T10:08:02.000Z",
      "name": "C2/infra IP",
      "pattern_type": "stix",
      "pattern": "[ipv4-addr:value = '185.252.24.78']",
      "valid_from": "2026-07-18T10:08:02.000Z"
    },
    {
      "type": "indicator",
      "spec_version": "2.1",
      "id": "indicator--e8bb427c-73ef-4862-af6f-d3c5187331c2",
      "created": "2026-07-18T10:08:02.000Z",
      "modified": "2026-07-18T10:08:02.000Z",
      "name": "C2/infra IP",
      "pattern_type": "stix",
      "pattern": "[ipv4-addr:value = '91.108.82.101']",
      "valid_from": "2026-07-18T10:08:02.000Z"
    },
    {
      "type": "indicator",
      "spec_version": "2.1",
      "id": "indicator--72a81d1c-e7a2-490a-b613-8f6f20631056",
      "created": "2026-07-18T10:08:02.000Z",
      "modified": "2026-07-18T10:08:02.000Z",
      "name": "C2/infra IP",
      "pattern_type": "stix",
      "pattern": "[ipv4-addr:value = '91.108.82.73']",
      "valid_from": "2026-07-18T10:08:02.000Z"
    },
    {
      "type": "indicator",
      "spec_version": "2.1",
      "id": "indicator--45581732-b048-475e-b2c9-c016ffd601f0",
      "created": "2026-07-18T10:08:02.000Z",
      "modified": "2026-07-18T10:08:02.000Z",
      "name": "C2/infra IP",
      "pattern_type": "stix",
      "pattern": "[ipv4-addr:value = '23.164.48.21']",
      "valid_from": "2026-07-18T10:08:02.000Z"
    }
  ]
}